{
  "lord": {
    "StrengthMultiplier": 1,
    "DotCount": 0,
    "DotColour": "None",
    "Type": "Arab"
  },
  "startTroops": {
    "normal": {
      "ArabSwordsman": 3,
      "ArabArcher": 6,
      "FireThrower": 3
    },
    "crusader": {
      "ArabSwordsman": 8,
      "ArabArcher": 50,
      "FireThrower": 8
    },
    "deathmatch": {
      "ArabSwordsman": 3,
      "ArabArcher": 6,
      "FireThrower": 3
    }
  },
  "aic": {
    "WallDecoration": 14,
    "Unknown001": 0,
    "Unknown002": 0,
    "Unknown003": 0,
    "Unknown004": 0,
    "Unknown005": 1,
    "CriticalPopularity": 6500,
    "LowestPopularity": 9700,
    "HighestPopularity": 9700,
    "TaxesMin": 0,
    "TaxesMax": 11,
    "Unknown011": 20,
    "Farm1": "AppleFarm",
    "Farm2": "HopFarm",
    "Farm3": "AppleFarm",
    "Farm4": "AppleFarm",
    "Farm5": "AppleFarm",
    "Farm6": "AppleFarm",
    "Farm7": "AppleFarm",
    "Farm8": "AppleFarm",
    "PopulationPerFarm": 2,
    "PopulationPerWoodcutter": 1,
    "PopulationPerQuarry": 9,
    "PopulationPerIronmine": 13,
    "PopulationPerPitchrig": 15,
    "MaxQuarries": 3,
    "MaxIronmines": 6,
    "MaxWoodcutters": 8,
    "MaxPitchrigs": 8,
    "MaxFarms": 15,
    "BuildInterval": 2,
    "ResourceRebuildDelay": 12,
    "MaxFood": 91,
    "MinimumApples": 11,
    "MinimumCheese": -1,
    "MinimumBread": -1,
    "MinimumWheat": -1,
    "MinimumHop": 1,
    "TradeAmountFood": 4,
    "TradeAmountEquipment": 2,
    "AIRequestDelay": 0,
    "MinimumGoodsRequiredAfterTrade": 0,
    "DoubleRationsFoodThreshold": 58,
    "MaxWood": 201,
    "MaxStone": 51,
    "MaxResourceOther": 10,
    "MaxEquipment": 2,
    "MaxBeer": 9,
    "MaxResourceVariance": 1,
    "RecruitGoldThreshold": 105,
    "BlacksmithSetting": "Maces",
    "FletcherSetting": "Crossbows",
    "PoleturnerSetting": "Spears",
    "SellResource01": "None",
    "SellResource02": "None",
    "SellResource03": "None",
    "SellResource04": "None",
    "SellResource05": "Wheat",
    "SellResource06": "None",
    "SellResource07": "Flour",
    "SellResource08": "Bows",
    "SellResource09": "Crossbows",
    "SellResource10": "Spears",
    "SellResource11": "Pikes",
    "SellResource12": "Maces",
    "SellResource13": "Swords",
    "SellResource14": "LeatherArmors",
    "SellResource15": "IronArmors",
    "DefWallPatrolRallyTime": 8,
    "DefWallPatrolGroups": 3,
    "DefSiegeEngineGoldThreshold": 900,
    "DefSiegeEngineBuildDelay": 55,
    "Unknown072": 42,
    "Unknown073": 14,
    "RecruitProbDefDefault": 56,
    "RecruitProbDefWeak": 78,
    "RecruitProbDefStrong": 23,
    "RecruitProbRaidDefault": 35,
    "RecruitProbRaidWeak": 22,
    "RecruitProbRaidStrong": 7,
    "RecruitProbAttackDefault": 9,
    "RecruitProbAttackWeak": 0,
    "RecruitProbAttackStrong": 70,
    "SortieUnitRangedMin": 3,
    "SortieUnitRanged": "ArabArcher",
    "SortieUnitMeleeMin": 4,
    "SortieUnitMelee": "Assassin",
    "DefDiggingUnitMax": 11,
    "DefDiggingUnit": "Slave",
    "RecruitInterval": 1,
    "RecruitIntervalWeak": 5,
    "RecruitIntervalStrong": 0,
    "DefTotal": 74,
    "OuterPatrolGroupsCount": 1,
    "OuterPatrolGroupsMove": "True",
    "OuterPatrolRallyDelay": 200,
    "DefWalls": 74,
    "DefUnit1": "FireThrower",
    "DefUnit2": "ArabArcher",
    "DefUnit3": "ArabArcher",
    "DefUnit4": "ArabArcher",
    "DefUnit5": "ArabArcher",
    "DefUnit6": "ArabArcher",
    "DefUnit7": "ArabArcher",
    "DefUnit8": "None",
    "RaidUnitsBase": 26,
    "RaidUnitsRandom": 16,
    "RaidUnit1": "Slave",
    "RaidUnit2": "None",
    "RaidUnit3": "None",
    "RaidUnit4": "None",
    "RaidUnit5": "None",
    "RaidUnit6": "None",
    "RaidUnit7": "None",
    "RaidUnit8": "None",
    "HarassingSiegeEngine1": "FireBallista",
    "HarassingSiegeEngine2": "Catapult",
    "HarassingSiegeEngine3": "FireBallista",
    "HarassingSiegeEngine4": "Catapult",
    "HarassingSiegeEngine5": "FireBallista",
    "HarassingSiegeEngine6": "None",
    "HarassingSiegeEngine7": "None",
    "HarassingSiegeEngine8": "None",
    "HarassingSiegeEnginesMax": 6,
    "RaidRetargetDelay": 1,
    "AttForceBase": 36,
    "AttForceRandom": 4,
    "AttForceSupportAllyThreshold": 0,
    "AttForceRallyPercentage": 35,
    "Unknown129": 100,
    "AttAssaultDelay": 5,
    "AttUnitPatrolRecommandDelay": 1,
    "Unknown132": 5,
    "SiegeEngine1": "FireBallista",
    "SiegeEngine2": "FireBallista",
    "SiegeEngine3": "FireBallista",
    "SiegeEngine4": "FireBallista",
    "SiegeEngine5": "FireBallista",
    "SiegeEngine6": "FireBallista",
    "SiegeEngine7": "FireBallista",
    "SiegeEngine8": "Trebuchet",
    "CowThrowInterval": 24,
    "Unknown142": 0,
    "AttMaxEngineers": 17,
    "AttDiggingUnit": "Slave",
    "AttDiggingUnitMax": 22,
    "AttUnitVanguard": "ArabArcher",
    "AttUnitVanguardMax": 52,
    "AttMaxAssassins": 20,
    "AttMaxLaddermen": 0,
    "AttMaxTunnelers": 0,
    "AttUnitPatrol": "Slinger",
    "AttUnitPatrolMax": 12,
    "AttUnitPatrolGroupsCount": 1,
    "AttUnitBackup": "None",
    "AttUnitBackupMax": 0,
    "AttUnitBackupGroupsCount": 0,
    "AttUnitEngage": "Assassin",
    "AttUnitEngageMax": 20,
    "AttUnitSiegeDef": "FireThrower",
    "AttUnitSiegeDefMax": 5,
    "AttUnitSiegeDefGroupsCount": 2,
    "AttUnitMain1": "ArabSwordsman",
    "AttUnitMain2": "ArabSwordsman",
    "AttUnitMain3": "ArabSwordsman",
    "AttUnitMain4": "Assassin",
    "AttMaxDefault": 200,
    "AttMainGroupsCount": 2,
    "TargetChoice": "Balanced"
  }
}